{
  "navLabel": "Get in touch",
  "heading": "Get in touch",
  "intro": "Whether you're considering therapy or coaching for yourself, or looking to book me to speak or run a workshop, I'd be glad to hear from you.",
  "paths": [
    {
      "eyebrow": "For individuals",
      "title": "Therapy & coaching",
      "body": "One-to-one support for men, in person or online — anxiety, relationships, addiction, masculinity and more.",
      "ctaLabel": "Book a free 15-minute consultation",
      "ctaHref": "#contact",
      "linkLabel": "About therapy & coaching",
      "linkHref": "/working-together"
    },
    {
      "eyebrow": "For organisations",
      "title": "Speaking & workshops",
      "body": "Keynotes and workplace workshops on men's mental health, masculinity and wellbeing — for workplaces, schools, universities and conferences.",
      "ctaLabel": "Enquire about speaking",
      "ctaHref": "mailto:chrishemmings@live.co.uk?subject=Speaking enquiry",
      "linkLabel": "See talks & workshops",
      "linkHref": "/public-speaking"
    }
  ],
  "whatToExpect": {
    "eyebrow": "If you're considering therapy",
    "title": "What happens next",
    "steps": [
      {
        "title": "Reach out",
        "body": "Send an email, call or text — whatever feels easiest. Tell me as much or as little as you like."
      },
      {
        "title": "A free 15-minute call",
        "body": "We'll have a no-obligation video chat about what's going on and whether we're a good fit."
      },
      {
        "title": "Your first session",
        "body": "If it feels right, we'll find a time that works and begin — at your pace."
      }
    ]
  },
  "reassurances": ["No obligation", "I reply personally", "Completely confidential"],
  "og": {
    "eyebrow": "Get in touch",
    "title": "Therapy, coaching & speaking",
    "subtitle": "For individuals and organisations",
    "cta": "Book a free 15-minute consultation"
  }
}
